Workbook

Sheet Assumptions
A1: APTOHIRE | FINANCIAL MODEL & PROJECTIONS
A2: Editable scenario model, INR, 5 fiscal years. All values below are illustrative planning assumptions—not actuals, commitments or forecasts validated with customers.
A4: Input / Assumption | B4: Value | C4: Unit / basis | D4: Rationale / status
A5: Starting paying institutions | B5: 2 | C5: institutions | D5: Illustrative launch cohort; replace with pipeline evidence.
A6: Annual new institutions added | B6: 5 | C6: institutions/year | D6: Illustrative sales capacity assumption.
A7: Annual institution churn | B7: 0.1 | C7: % | D7: Assumed churn; not observed.
A8: Annual licence price | B8: 600000 | C8: INR/institution/year | D8: Illustrative ₹6 lakh; validate willingness to pay.
A9: Pilot revenue per new institution | B9: 100000 | C9: INR/one-time pilot | D9: Illustrative; assumed for new institutions.
A10: Pilot conversion rate | B10: 0.5 | C10: % of new institutions | D10: Assumed conversion; not validated.
A11: Implementation revenue per new institution | B11: 50000 | C11: INR/one-time | D11: Illustrative onboarding/integration fee.
A12: Direct service cost per new institution | B12: 25000 | C12: INR/one-time | D12: Illustrative delivery cost.
A13: Annual direct support cost per active institution | B13: 60000 | C13: INR/institution/year | D13: Illustrative support/hosting allocation.
A14: Annual payroll / contractor cost | B14: 3600000 | C14: INR/year | D14: Illustrative lean team budget; replace with quotes.
A15: Annual sales & marketing cost | B15: 900000 | C15: INR/year | D15: Illustrative; includes outreach and events.
A16: Annual G&A / legal / accounting | B16: 600000 | C16: INR/year | D16: Illustrative operating overhead.
... A20: Tax / financing / depreciation | B20: 0 | C20: INR/year | D20: Simplified pre-tax, pre-financing operating model; replace with accountant-reviewed schedules.

Sheet 5Y P&L
A1: 5-YEAR PROFIT & LOSS (SCENARIO)
A3: Metric | B3: Year 1 | C3: Year 2 | D3: Year 3 | E3: Year 4 | F3: Year 5
A4: New institutions | B4: =Assumptions!$B$6 | C4: =Assumptions!$B$6 | D4: =Assumptions!$B$6 | E4: =Assumptions!$B$6 | F4: =Assumptions!$B$6
A5: Opening active institutions | B5: =Assumptions!$B$5 | C5: =B8 | D5: =C8 | E5: =D8 | F5: =E8
A6: Churned institutions | B6: =B5*Assumptions!$B$7 | C6: =C5*Assumptions!$B$7 | D6: =D5*Assumptions!$B$7 | E6: =E5*Assumptions!$B$7 | F6: =F5*Assumptions!$B$7
A7: New annual licence conversions | B7: =B4*Assumptions!$B$10 | C7: =C4*Assumptions!$B$10 | D7: =D4*Assumptions!$B$10 | E7: =E4*Assumptions!$B$10 | F7: =F4*Assumptions!$B$10
A8: Ending active institutions | B8: =B5-B6+B7 | C8: =C5-C6+C7 | D8: =D5-D6+D7 | E8: =E5-E6+E7 | F8: =F5-F6+F7
A9: Recurring licence revenue | B9: =(B5+B8)/2*Assumptions!$B$8 | C9: =(C5+C8)/2*Assumptions!$B$8 | D9: =(D5+D8)/2*Assumptions!$B$8 | E9: =(E5+E8)/2*Assumptions!$B$8 | F9: =(F5+F8)/2*Assumptions!$B$8
A10: Pilot revenue | B10: =B4*Assumptions!$B$9 | C10: =C4*Assumptions!$B$9 | D10: =D4*Assumptions!$B$9 | E10: =E4*Assumptions!$B$9 | F10: =F4*Assumptions!$B$9
A11: Implementation revenue | B11: =B4*Assumptions!$B$11 | C11: =C4*Assumptions!$B$11 | D11: =D4*Assumptions!$B$11 | E11: =E4*Assumptions!$B$11 | F11: =F4*Assumptions!$B$11
A12: TOTAL REVENUE | B12: =SUM(B9:B11) | C12: =SUM(C9:C11) | D12: =SUM(D9:D11) | E12: =SUM(E9:E11) | F12: =SUM(F9:F11)
A13: Direct service cost | B13: =B4*Assumptions!$B$12 | C13: =C4*Assumptions!$B$12 | D13: =D4*Assumptions!$B$12 | E13: =E4*Assumptions!$B$12 | F13: =F4*Assumptions!$B$12
A14: Direct support cost | B14: =B8*Assumptions!$B$13 | C14: =C8*Assumptions!$B$13 | D14: =D8*Assumptions!$B$13 | E14: =E8*Assumptions!$B$13 | F14: =F8*Assumptions!$B$13
A15: TOTAL COST OF REVENUE | B15: =SUM(B13:B14) | C15: =SUM(C13:C14) | D15: =SUM(D13:D14) | E15: =SUM(E13:E14) | F15: =SUM(F13:F14)
A16: GROSS PROFIT | B16: =B12-B15 | C16: =C12-C15 | D16: =D12-D15 | E16: =E12-E15 | F16: =F12-F15
A17: Payroll / contractors | B17: =Assumptions!$B$14 | C17: =B17*(1+Assumptions!$B$18) | D17: =C17*(1+Assumptions!$B$18) | E17: =D17*(1+Assumptions!$B$18) | F17: =E17*(1+Assumptions!$B$18)
A18: Sales & marketing | B18: =Assumptions!$B$15 | C18: =B18*(1+Assumptions!$B$18) | D18: =C18*(1+Assumptions!$B$18) | E18: =D18*(1+Assumptions!$B$18) | F18: =E18*(1+Assumptions!$B$18)
A19: G&A / legal / accounting | B19: =Assumptions!$B$16 | C19: =B19*(1+Assumptions!$B$18) | D19: =C19*(1+Assumptions!$B$18) | E19: =D19*(1+Assumptions!$B$18) | F19: =E19*(1+Assumptions!$B$18)
A20: Product / cloud / security | B20: =Assumptions!$B$17 | C20: =B20*(1+Assumptions!$B$18) | D20: =C20*(1+Assumptions!$B$18) | E20: =D20*(1+Assumptions!$B$18) | F20: =E20*(1+Assumptions!$B$18)
A21: TOTAL OPERATING EXPENSES | B21: =SUM(B17:B20) | C21: =SUM(C17:C20) | D21: =SUM(D17:D20) | E21: =SUM(E17:E20) | F21: =SUM(F17:F20)
A22: OPERATING PROFIT / (LOSS) | B22: =B16-B21 | C22: =C16-C21 | D22: =D16-D21 | E22: =E16-E21 | F22: =F16-F21
A23: Operating margin | B23: =IFERROR(B22/B12,0) | C23: =IFERROR(C22/C12,0) | D23: =IFERROR(D22/D12,0) | E23: =IFERROR(E22/E12,0) | F23: =IFERROR(F22/F12,0)

Sheet Cash Flow
A1: CASH FLOW & RUNWAY (SIMPLIFIED)
A3: Metric | B3: Year 1 | C3: Year 2 | D3: Year 3 | E3: Year 4 | F3: Year 5
A4: Opening cash | B4: =Assumptions!$B$19 | C4: =B9 | D4: =C9 | E4: =D9 | F4: =E9
A5: Operating profit / (loss) | B5: ='5Y P&L'!B22 | C5: ='5Y P&L'!C22 | D5: ='5Y P&L'!D22 | E5: ='5Y P&L'!E22 | F5: ='5Y P&L'!F22
A6: Capital expenditure / one-off build | B6: 0 | C6: 0 | D6: 0 | E6: 0 | F6: 0
A7: Financing raised | B7: 0 | C7: 0 | D7: 0 | E7: 0 | F7: 0
A8: Net cash movement | B8: =B5-B6+B7 | C8: =C5-C6+C7 | D8: =D5-D6+D7 | E8: =E5-E6+E7 | F8: =F5-F6+F7
A9: Closing cash | B9: =B4+B8 | C9: =C4+C8 | D9: =D4+D8 | E9: =E4+E8 | F9: =F4+F8
A10: Average monthly net burn (if negative) | B10: =IF(B8<0,-B8/12,0) | C10: =IF(C8<0,-C8/12,0) | D10: =IF(D8<0,-D8/12,0) | E10: =IF(E8<0,-E8/12,0) | F10: =IF(F8<0,-F8/12,0)
A11: Runway months (if net burn) | B11: =IF(B10>0,B4/B10,0) | C11: =IF(C10>0,C4/C10,0) | D11: =IF(D10>0,D4/D10,0) | E11: =IF(E10>0,E4/E10,0) | F11: =IF(F10>0,F4/F10,0)
A14: Model notes
A15: Operating profit is used as a simplified cash proxy. Actual cash flow requires receivables, payables, taxes, working capital, capex, debt/equity proceeds and timing.
A16: Enter capital expenditure and financing by year in rows 6–7. Negative closing cash signals a funding or cost/revenue timing issue.
A17: Runway months are only a rough proxy using opening cash divided by annual net burn / 12; they are not a substitute for monthly cash forecasting.
A18: All inputs are illustrative. Use actual payroll quotes, cloud bills, pilot terms, sales cycle, conversion and churn data before investor use.

Sheet Burn Detail
A1: MONTHLY BURN-RATE TRACKER
A3: Cost category | B3: Monthly plan (INR) | C3: Monthly actual (INR) | D3: Variance (Actual - Plan)
A4: Payroll / contractors | B4: 0 | C4: 0 | D4: =C4-B4
A5: Cloud / hosting / AI API | B5: 0 | C5: 0 | D5: =C5-B5
A6: Software / tools | B6: 0 | C6: 0 | D6: =C6-B6
A7: Sales / marketing / events | B7: 0 | C7: 0 | D7: =C7-B7
A8: Legal / accounting / compliance | B8: 0 | C8: 0 | D8: =C8-B8
A9: Travel / meetings | B9: 0 | C9: 0 | D9: =C9-B9
A10: Customer support / delivery | B10: 0 | C10: 0 | D10: =C10-B10
A11: Other | B11: 0 | C11: 0 | D11: =C11-B11
A12: TOTAL MONTHLY BURN | B12: =SUM(B4:B11) | C12: =SUM(C4:C11) | D12: =C12-B12
A14: Net burn = cash operating outflows minus cash operating inflows in the month. Keep planned and actual values separate.
